cli.py
main.py
ezon_gpx-1.0.3.dist-info/LICENSE
ezon_gpx-1.0.3.dist-info/METADATA
ezon_gpx-1.0.3.dist-info/WHEEL
ezon_gpx-1.0.3.dist-info/entry_points.txt
ezon_gpx-1.0.3.dist-info/top_level.txt
ezon_gpx-1.0.3.dist-info/RECORD
