Metadata-Version: 2.2
Name: ezon-gpx
Version: 1.0.3
Summary: convert Ezon gpx files.
Author: uiolee
Maintainer: uiolee
License: MPL 2.0
Project-URL: Homepage, https://github.com/uiolee/ezon-gpx
Project-URL: Repository, https://github.com/uiolee/ezon-gpx.git
Project-URL: Issues, https://github.com/uiolee/ezon-gpx/issues
Keywords: ezon,gpx,xml,running_page
Classifier: Development Status :: 4 - Beta
Classifier: Environment :: Console
Classifier: Intended Audience :: Developers
Classifier: Intended Audience :: End Users/Desktop
Classifier: Intended Audience :: Healthcare Industry
Classifier: Topic :: Text Processing :: Markup :: XML
Classifier: Topic :: File Formats
Classifier: Topic :: Utilities
Classifier: License :: OSI Approved :: Mozilla Public License 2.0 (MPL 2.0)
Classifier: Natural Language :: English
Classifier: Operating System :: Microsoft :: Windows
Classifier: Operating System :: POSIX :: Linux
Classifier: Operating System :: MacOS
Classifier: Programming Language :: Python :: 3.11
License-File: LICENSE
